bugbreaker/__init__.py
bugbreaker/__main__.py
bugbreaker/bugbreaker.py
bugbreaker/utilities/__init__.py
bugbreaker/utilities/chatgpt.py
bugbreaker/utilities/code_execution.py
bugbreaker/utilities/parsers.py
bugbreaker/utilities/printers.py
bugbreaker-1.5.0.dist-info/METADATA
bugbreaker-1.5.0.dist-info/WHEEL
bugbreaker-1.5.0.dist-info/entry_points.txt
bugbreaker-1.5.0.dist-info/top_level.txt
bugbreaker-1.5.0.dist-info/RECORD
